ecg_transform/inp.py
ecg_transform/sample.py
ecg_transform/t/base.py
ecg_transform/t/clean.py
ecg_transform/t/common.py
ecg_transform/t/cut.py
ecg_transform/t/filter.py
ecg_transform/t/scale.py
ecg_transform/utils/common.py
ecg_transform-0.1.3.dist-info/licenses/LICENSE
ecg_transform-0.1.3.dist-info/METADATA
ecg_transform-0.1.3.dist-info/WHEEL
ecg_transform-0.1.3.dist-info/top_level.txt
ecg_transform-0.1.3.dist-info/RECORD
