Metadata-Version: 2.4
Name: ecg-transform
Version: 0.1.3
Summary: Package curating cohesive training & inference pipelines for ECG analysis.
Author-email: Kaden McKeen <kaden.mckeen@mail.utoronto.ca>
License: BSD 3-Clause License
Project-URL: Homepage, https://github.com/KadenMc/ecg-transform
Project-URL: Bug Tracker, https://github.com/KadenMc/ecg-transform/issues
Keywords: ecg,ekg,electrocardiogram,transform,transformation,transformations,augment,augmentation,augmentations
Classifier: Programming Language :: Python :: 3
Classifier: Operating System :: OS Independent
Classifier: License :: OSI Approved :: BSD License
Requires-Python: >=3.7
License-File: LICENSE
Requires-Dist: numpy>=2.1.3
Requires-Dist: scipy>=1.14.0
Dynamic: license-file
